osa/__init__.py
osa/client.py
osa/message.py
osa/method.py
osa/wsdl.py
osa/xmlnamespace.py
osa/xmlparser.py
osa/xmlschema.py
osa/xmltypes.py
osa-0.2.3.dist-info/COPYING
osa-0.2.3.dist-info/METADATA
osa-0.2.3.dist-info/WHEEL
osa-0.2.3.dist-info/top_level.txt
osa-0.2.3.dist-info/RECORD
