Metadata-Version: 1.1
Name: osa
Version: 0.2.3
Summary: Python fast/slim/convenient SOAP/WSDL client.
Home-page: https://github.com/baserge/osa
Author: Sergey A. Bozhenkov
Author-email: ba-serge@yandex.ru
License: LGPLv3
Download-URL: https://github.com/baserge/osa/archive/master.zip
Platform: UNKNOWN
Classifier: Development Status :: 5 - Production/Stable
Classifier: Environment :: Console
Classifier: Environment :: Web Environment
Classifier: Intended Audience :: Developers
Classifier: Intended Audience :: End Users/Desktop
Classifier: License :: OSI Approved :: GNU Lesser General Public License v3 or later (LGPLv3+)
Classifier: Natural Language :: English
Classifier: Operating System :: OS Independent
Classifier: Programming Language :: Python
Classifier: Topic :: Internet
Classifier: Topic :: Internet :: WWW/HTTP
Classifier: Topic :: Software Development :: Libraries
Classifier: Topic :: Software Development :: Object Brokering
